aiolinkding/__init__.py
aiolinkding/bookmark.py
aiolinkding/client.py
aiolinkding/const.py
aiolinkding/errors.py
aiolinkding/py.typed
aiolinkding/tag.py
aiolinkding/user.py
aiolinkding/util/__init__.py
aiolinkding-2025.2.0.dist-info/LICENSE
aiolinkding-2025.2.0.dist-info/METADATA
aiolinkding-2025.2.0.dist-info/WHEEL
aiolinkding-2025.2.0.dist-info/RECORD
